{
  "publicPath": "/_nuxt/",
  "all": [
    "layouts/errorLayout.0c77352fe1c9f9b23a23.js",
    "pages/_page.759d6f0268e4d85916e6.js",
    "pages/layout/blog-header.398143550a705bc3d878.js",
    "pages/layout/blog-footer.29adc7077c2852f51c03.js",
    "pages/layout/blog-rg.7dd5614747197b5f8a3c.js",
    "layouts/default.bc81a58daf87a52e0af7.js",
    "pages/detail/_id.43084be85067b23e0219.js",
    "vendor.3a30a35ea292abb15fe5.js",
    "app.28d02ccde973707ad3c7.js",
    "manifest.21832c51f39ec3ff1637.js",
    "LICENSES",
    "index.spa.html",
    "index.ssr.html"
  ],
  "initial": [
    "manifest.21832c51f39ec3ff1637.js",
    "vendor.3a30a35ea292abb15fe5.js",
    "app.28d02ccde973707ad3c7.js"
  ],
  "async": [
    "layouts/errorLayout.0c77352fe1c9f9b23a23.js",
    "pages/_page.759d6f0268e4d85916e6.js",
    "pages/layout/blog-header.398143550a705bc3d878.js",
    "pages/layout/blog-footer.29adc7077c2852f51c03.js",
    "pages/layout/blog-rg.7dd5614747197b5f8a3c.js",
    "layouts/default.bc81a58daf87a52e0af7.js",
    "pages/detail/_id.43084be85067b23e0219.js"
  ],
  "modules": {
    "38752804": [
      1
    ],
    "58187037": [
      7
    ],
    "68911329": [
      7
    ],
    "73095539": [
      7
    ],
    "81639118": [
      7
    ],
    "86370228": [
      7
    ],
    "92311784": [
      7
    ],
    "ff1ae82c": [
      7
    ],
    "9057fe72": [
      7
    ],
    "08150377": [
      8
    ],
    "4ae729c2": [
      7
    ],
    "d6aef67c": [
      7
    ],
    "66859b98": [
      7
    ],
    "39efa65b": [
      7
    ],
    "2f203024": [
      8
    ],
    "5508f4a4": [
      7
    ],
    "43b0284e": [
      8
    ],
    "21a285b4": [
      6
    ],
    "7ce2ebf5": [
      7
    ],
    "49a3aaf9": [
      7
    ],
    "5431bc04": [
      7
    ],
    "2404ba8a": [
      8
    ],
    "bd4d29d6": [
      7
    ],
    "03501f4c": [
      8
    ],
    "6500d577": [
      7
    ],
    "69106a6e": [
      8
    ],
    "32f403b6": [
      7
    ],
    "4bab49d9": [
      7
    ],
    "eb507248": [
      5
    ],
    "746db462": [
      7
    ],
    "a117dd30": [
      6
    ],
    "539d2486": [
      7
    ],
    "53a39b6c": [
      7
    ],
    "dc00deca": [
      0
    ],
    "612fafb6": [
      7
    ],
    "b216e4dc": [
      7
    ],
    "444fbe86": [
      8
    ],
    "7e350e5d": [
      7
    ],
    "06150579": [
      7
    ],
    "fb2d6868": [
      7
    ],
    "1d860916": [
      7
    ],
    "6225c43a": [
      7
    ],
    "498701ac": [
      7
    ],
    "61916d02": [
      7
    ],
    "46fe5426": [
      5
    ],
    "65c2df14": [
      7
    ],
    "7f247442": [
      7
    ],
    "21bd670d": [
      7
    ],
    "54463a01": [
      7
    ],
    "446b9658": [
      7
    ],
    "286462e8": [
      7
    ],
    "fabecc80": [
      7
    ],
    "24449d7c": [
      8
    ],
    "2a118058": [
      7
    ],
    "39e76e81": [
      7
    ],
    "f82d3a1e": [
      7
    ],
    "34e533d0": [
      8
    ],
    "425d4be3": [
      8
    ],
    "0febd7bc": [
      8
    ],
    "5444b1de": [
      8
    ],
    "2397c318": [
      7
    ],
    "53c4c87b": [
      7
    ],
    "b543524a": [
      7
    ],
    "7cdc1a64": [
      7
    ],
    "7798e7ef": [
      8
    ],
    "edf42d56": [
      7
    ],
    "06daea34": [
      7
    ],
    "313f955b": [
      7
    ],
    "786e76ec": [
      5
    ],
    "11d8ee9f": [
      7
    ],
    "1f466d6a": [
      7
    ],
    "82d625f6": [
      7
    ],
    "8f9c9dfc": [
      7
    ],
    "01086233": [
      7
    ],
    "565fd30e": [
      7
    ],
    "2d8010ef": [
      7
    ],
    "8a754d54": [
      6
    ],
    "1afb9a5e": [
      8
    ],
    "fafed0d8": [
      1
    ],
    "a2169314": [
      8
    ],
    "ae7bd890": [
      8
    ],
    "ad8578b0": [
      7
    ],
    "3fa01196": [
      7
    ],
    "6064d14b": [
      7
    ],
    "4986df32": [
      7
    ],
    "90f546d8": [
      7
    ],
    "4aab8af5": [
      7
    ],
    "12ca151f": [
      7
    ],
    "2544342d": [
      8
    ],
    "16cd0574": [
      7
    ],
    "0aba2b41": [
      1
    ],
    "47382d59": [
      7
    ],
    "0990925c": [
      8
    ],
    "7ea1eb69": [
      7
    ],
    "11998c37": [
      7
    ],
    "10cdf43b": [
      0
    ],
    "15a43496": [
      8
    ],
    "4896846a": [
      7
    ],
    "0daddd11": [
      8
    ],
    "f2efa19e": [
      7
    ],
    "e8c91b3a": [
      7
    ],
    "05a5e758": [
      7
    ],
    "da343402": [
      7
    ],
    "736c1af6": [
      8
    ],
    "6c2b91b7": [
      7
    ],
    "235c5103": [
      7
    ],
    "59af6616": [
      8
    ],
    "982ae136": [
      7
    ],
    "252c2fce": [
      7
    ],
    "69f230fc": [
      7
    ],
    "382e281c": [
      8
    ],
    "55a4f804": [
      7
    ],
    "afd984d0": [
      7
    ],
    "6dd6af69": [
      7
    ],
    "5922a4dd": [
      7
    ],
    "3f8ef76e": [
      8
    ],
    "772cc7f7": [
      7
    ],
    "c77a5466": [
      7
    ],
    "4d185862": [
      7
    ],
    "291b5954": [
      7
    ],
    "2f18f1a9": [
      7
    ],
    "60ccf5bb": [
      7
    ],
    "8a106218": [
      7
    ],
    "68ee1343": [
      7
    ],
    "7eb4e854": [
      7
    ],
    "ebbcb11e": [
      7
    ],
    "8fd38f0e": [
      7
    ],
    "1c51e2c0": [
      7
    ],
    "fc43806a": [
      7
    ],
    "5297dc4b": [
      7
    ],
    "0c03b13f": [
      7
    ],
    "376439fe": [
      7
    ],
    "e6ca51c6": [
      7
    ],
    "53c23485": [
      8
    ],
    "7117a69c": [
      1
    ],
    "3edeba5d": [
      7
    ],
    "7e43489a": [
      7
    ],
    "5ffe5cc8": [
      7
    ],
    "4f81cfe8": [
      7
    ],
    "578100c8": [
      7
    ],
    "1f82517c": [
      7
    ],
    "2d09e1c8": [
      8
    ],
    "3fea364c": [
      7
    ],
    "7d18dfde": [
      7
    ],
    "2b53a4ae": [
      8
    ],
    "99631b8a": [
      7
    ],
    "dda40f50": [
      8
    ],
    "d6989de6": [
      7
    ],
    "8a40df88": [
      7
    ],
    "7ce0a61a": [
      7
    ],
    "64fc1ac2": [
      1
    ],
    "63b1f272": [
      7
    ],
    "6d22c6aa": [
      1
    ],
    "4af6a90e": [
      7
    ],
    "a0796eee": [
      7
    ],
    "1352105b": [
      8
    ],
    "b7bee972": [
      7
    ],
    "ea88bd68": [
      7
    ],
    "b29d9210": [
      7
    ],
    "f3054d14": [
      8
    ],
    "2645c2c6": [
      7
    ],
    "c9e031ce": [
      7
    ],
    "4bfb1a02": [
      8
    ],
    "36f334c5": [
      7
    ],
    "98561ba6": [
      7
    ],
    "a09d4bbe": [
      8
    ],
    "6bfe33fa": [
      8
    ],
    "2f871dd9": [
      8
    ],
    "3256d3e4": [
      7
    ],
    "a4b49f22": [
      8
    ],
    "45e4ad21": [
      7
    ],
    "0e42a93e": [
      7
    ],
    "b8874bc4": [
      7
    ],
    "45ef56c6": [
      7
    ],
    "d9066d84": [
      7
    ],
    "17dbbff5": [
      7
    ],
    "0d538719": [
      8
    ],
    "64226c7d": [
      7
    ],
    "60cacb68": [
      8
    ],
    "1d0db36d": [
      1
    ],
    "2ea586e5": [
      7
    ],
    "810bfacc": [
      7
    ],
    "1e8bf479": [
      1
    ]
  }
}